awa/__init__.py
awa/shell/__init__.py
awa/shell/usage.py
awa/src/temp.txt
package_name/__init__.py
package_name/shell/__init__.py
package_name/shell/usage.py
package_name/src/temp.txt
awa-0.0.1.dist-info/LICENSE
awa-0.0.1.dist-info/METADATA
awa-0.0.1.dist-info/WHEEL
awa-0.0.1.dist-info/entry_points.txt
awa-0.0.1.dist-info/top_level.txt
awa-0.0.1.dist-info/zip-safe
awa-0.0.1.dist-info/RECORD
